bountyful/__init__.py
bountyful/crowd.py
bountyful/optim.py
bountyful-0.0.1.dist-info/METADATA
bountyful-0.0.1.dist-info/WHEEL
bountyful-0.0.1.dist-info/top_level.txt
bountyful-0.0.1.dist-info/RECORD
