Metadata-Version: 2.1
Name: bountyful
Version: 0.0.1
Summary: Bountyful API
Home-page: https://bountyful.ai
Author: Gianluca Truda
Author-email: gianluca@bountyful.ai
License: UNKNOWN
Platform: UNKNOWN
Classifier: Programming Language :: Python :: 3
Classifier: License :: OSI Approved :: MIT License
Classifier: Operating System :: OS Independent
Requires-Python: >=3.7
